[
    {
        "nickname": "mike",
        "email": "mike@mail.ru",
        "id": "0000000000001"
    },
    {
        "nickname": "mishel",
        "email": "mishel@mail.ru",
        "id": "0000000000002"
    },
    {
        "nickname": "adel",
        "email": "adel@mail.ru",
        "id": "0000000000003"
    },
    {
        "nickname": "keks",
        "email": "keks@mail.ru",
        "id": "0000000000004"
    },
    {
        "nickname": "kamila",
        "email": "kamila@mail.ru",
        "id": "0000000000005"
    },
    {
        "nickname": "dad",
        "email": "dad@mail.ru",
        "id": "656961fa37cc2"
    },
    {
        "nickname": "mama",
        "email": "mama@yandex.ru",
        "id": "656968b2de339"
    },
    {
        "nickname": "tatiana",
        "email": "tatty@ya.com",
        "id": "6569694504957"
    },
    {
        "nickname": "love",
        "email": "lovvv@ya.com",
        "id": "65696a2dcbde5"
    },
    {
        "nickname": "ewa",
        "email": "ewa555@mail.ru",
        "id": "6569763fad98c"
    },
    {
        "nickname": "gol",
        "email": "gol@ya.com",
        "id": "6569a6129f817"
    },
    {
        "nickname": "olya",
        "email": "ola123@mail.ru",
        "id": "6569a68ce75d4"
    },
    {
        "nickname": "sara",
        "email": "sara56@ya.com",
        "id": "6569a88d6b5ee"
    },
    {
        "nickname": "hil",
        "email": "hil@ya.com",
        "id": "6569a91b4729b"
    },
    {
        "nickname": "mike13",
        "email": "mike13@ya.com",
        "id": "6569a95c14787"
    },
    {
        "nickname": "bella13490892",
        "email": "bella13490892@mail.ru",
        "id": "6569a99ed47a5"
    },
    {
        "nickname": "daster",
        "email": "daster@mail.ru",
        "id": "6569ad0d2ec9f"
    },
    {
        "nickname": "filler",
        "email": "filler@mail.ru",
        "id": "657a7d6739515"
    }
]